tensorfree/Tensorfree.py
tensorfree/__init__.py
tensorfree/_version.py
tensorfree/model/__init__.py
tensorfree/model/pretrain.py
tensorfree/model/pretrain_factory.py
tensorfree/utils/__init__.py
tensorfree/utils/label.py
tensorfree/utils/preprocess.py
tensorfree/utils/wrappers.py
tensorfree-0.1.4.dist-info/AUTHORS.rst
tensorfree-0.1.4.dist-info/LICENSE
tensorfree-0.1.4.dist-info/METADATA
tensorfree-0.1.4.dist-info/WHEEL
tensorfree-0.1.4.dist-info/entry_points.txt
tensorfree-0.1.4.dist-info/top_level.txt
tensorfree-0.1.4.dist-info/RECORD
